spec_classes/__init__.py
spec_classes/_version.py
spec_classes/errors.py
spec_classes/spec_class.py
spec_classes/collections/__init__.py
spec_classes/collections/base.py
spec_classes/collections/mappings.py
spec_classes/collections/sequences.py
spec_classes/collections/sets.py
spec_classes/methods/__init__.py
spec_classes/methods/base.py
spec_classes/methods/core.py
spec_classes/methods/scalar.py
spec_classes/methods/toplevel.py
spec_classes/methods/collections/__init__.py
spec_classes/methods/collections/mappings.py
spec_classes/methods/collections/sequences.py
spec_classes/methods/collections/sets.py
spec_classes/types/__init__.py
spec_classes/types/alias.py
spec_classes/types/attr.py
spec_classes/types/attr_proxy.py
spec_classes/types/keyed.py
spec_classes/types/missing.py
spec_classes/types/spec_property.py
spec_classes/types/validated.py
spec_classes/utils/__init__.py
spec_classes/utils/method_builder.py
spec_classes/utils/mutation.py
spec_classes/utils/naming.py
spec_classes/utils/stackdepth.py
spec_classes/utils/type_checking.py
spec_classes/utils/weakref_cache.py
spec_classes-1.5.13.dist-info/METADATA
spec_classes-1.5.13.dist-info/WHEEL
spec_classes-1.5.13.dist-info/licenses/LICENSE
spec_classes-1.5.13.dist-info/RECORD
