Metadata-Version: 2.4
Name: spec-classes
Version: 1.5.13
Summary: Represent type-checked specifications as Python classes and incrementally build them.
Project-URL: repository, https://github.com/matthewwardrop/spec-classes
Project-URL: documentation, https://matthewwardrop.github.io/spec-classes
Author-email: Matthew Wardrop <mpwardrop@gmail.com>
License-Expression: MIT
License-File: LICENSE
Classifier: Development Status :: 5 - Production/Stable
Classifier: Environment :: Console
Classifier: Intended Audience :: Developers
Classifier: Intended Audience :: Information Technology
Classifier: Intended Audience :: Science/Research
Classifier: License :: OSI Approved :: MIT License
Classifier: Programming Language :: Python :: 3.7
Classifier: Programming Language :: Python :: 3.8
Classifier: Programming Language :: Python :: 3.9
Classifier: Programming Language :: Python :: 3.10
Classifier: Programming Language :: Python :: 3.11
Classifier: Programming Language :: Python :: 3.12
Requires-Python: >=3.7.2
Requires-Dist: cached-property>=1.5.2
Requires-Dist: inflect>=5.0.0
Requires-Dist: lazy-object-proxy>=1.5.0
Requires-Dist: typing-extensions>=4.1
